[
  {
    "id": "question-undefined",
    "difficulty": "ساده",
    "topics": [
      "تالیفی",
      "رضا ادیبی",
      "ریاضی و فیزیک",
      "دوازدهم",
      "هندسه",
      "فصل 1: ماتریس و کاربردها",
      "درس اول: ماتریس و اعمال روی ماتریسها",
      "تعریف ماتریسهای خاص و مقدمات ماتریس"
    ],
    "question": "میخواهیم اطلاعات 15 تیم فوتبال را که در یک لیگ همگی حضور دارند، در یک جدول که در آن تعداد بازی، برد، باخت، تساوی، گل زده، گل خورده و امتیاز است نمایش دهیم. این اطلاعات را بهصورت آرایشی از اعداد درون کروشه محصور میکنیم. این نمایش یک............... است.",
    "options": [
      "ماتریس $15\\times 6$",
      "ماتریس $15\\times 7$",
      "ماتریس $14\\times 6$",
      "ماتریس $16\\times 7$"
    ],
    "answer_index": null,
    "answer_text": null,
    "explanation": "پس در نهایت یک ماتریس $15\\times 7$ یا $7\\times 15$ خواهیم داشت که در صورت تعیین وضعیت حالت قرارگیری تیمها در جدول میتواند فقط یکی از حالات $15\\times 7$ یا $7\\times 15$ پاسخ باشد. چون در اینجا بحثی در این مورد نشده است، پس هر 2 حالت میتواند باشد. بنابراین گزینۀ 2 صحیح است."
  }
]