[
  {
    "id": "question-undefined",
    "difficulty": "متوسط",
    "topics": [
      "تالیفی",
      "سیدمحمدرضا حسینی فرد",
      "ریاضی و فیزیک",
      "دوازدهم",
      "هندسه",
      "فصل 1: ماتریس و کاربردها",
      "درس اول: ماتریس و اعمال روی ماتریسها",
      "ضرب ماتریسها و خواص عمل ضرب"
    ],
    "question": "در ماتریس ${{A}^{101}}={{\\left[ \\begin{matrix} 1 & 0 \\\\ 1 & 2 \\\\ \\end{matrix} \\right]}^{101}}$ جمع درایهها چقدر است؟",
    "options": [
      "${{2}^{202}}-1$",
      "${{2}^{202}}$",
      "${{2}^{101}}+2$",
      "${{2}^{102}}$"
    ],
    "answer_index": 4,
    "answer_text": "${{2}^{102}}$",
    "explanation": "ابتدا ماتریسهای ${{A}^{2}}$ و ${{A}^{3}}$ را به دست میآوریم تا بتوانیم برای ${{A}^{101}}$ به یک الگو برسیم: $\\begin{aligned} & {{A}^{2}}=\\left[ \\begin{matrix} 1 & 0 \\\\ 1 & 2 \\\\ \\end{matrix} \\right]\\left[ \\begin{matrix} 1 & 0 \\\\ 1 & 2 \\\\ \\end{matrix} \\right]=\\left[ \\begin{matrix} 1 & 0 \\\\ 3 & 4 \\\\ \\end{matrix} \\right] \\\\ & {{A}^{3}}=\\left[ \\begin{matrix} 1 & 0 \\\\ 1 & 2 \\\\ \\end{matrix} \\right]\\left[ \\begin{matrix} 1 & 0 \\\\ 3 & 4 \\\\ \\end{matrix} \\right]=\\left[ \\begin{matrix} 1 & 0 \\\\ 7 & 8 \\\\ \\end{matrix} \\right] \\\\ \\end{aligned}$ سپس میتوانیم ${{A}^{101}}$ را به صورت زیر بنویسیم: ${{A}^{101}}=\\left[ \\begin{matrix} 1 & 0 \\\\ {{2}^{101}}-1 & {{2}^{101}} \\\\ \\end{matrix} \\right]\\Rightarrow \\text{جمع درایهها }={{2}^{101}}-1+1+{{2}^{101}}=2\\times {{2}^{101}}={{2}^{102}}$"
  }
]